setup.py
src/z3tinymce/__init__.py
src/z3tinymce/configure.zcml
src/z3tinymce/reslib.zcml
src/z3tinymce.egg-info/PKG-INFO
src/z3tinymce.egg-info/SOURCES.txt
src/z3tinymce.egg-info/dependency_links.txt
src/z3tinymce.egg-info/not-zip-safe
src/z3tinymce.egg-info/requires.txt
src/z3tinymce.egg-info/top_level.txt