Metadata-Version: 1.1
Name: z3tinymce
Version: 0.9
Summary: Zope3 Package of TinyMCE
Home-page: http://pypi.python.org/pypi/z3tinymce
Author: Miano Njoka
Author-email: miano@parliaments.info
License: UNKNOWN
Platform: UNKNOWN
Classifier: Programming Language :: Python
Classifier: Environment :: Web Environment
Classifier: Topic :: Internet :: WWW/HTTP :: WSGI :: Application
Classifier: Framework :: Zope3
